portalnews/__init__.py
portalnews/daum/__init__.py
portalnews/daum/_crawler.py
portalnews/daum/const.py
portalnews/daum/parser.py
portalnews/nate/__init__.py
portalnews/nate/crawler.py
portalnews/nate/parser.py
portalnews/naver/__init__.py
portalnews/naver/_crawler.py
portalnews/naver/const.py
portalnews/naver/nnkit.py
portalnews/naver/parser.py
portalnews-0.1.1.dist-info/METADATA
portalnews-0.1.1.dist-info/WHEEL
portalnews-0.1.1.dist-info/top_level.txt
portalnews-0.1.1.dist-info/RECORD
