Metadata-Version: 2.1
Name: portalnews
Version: 0.1.1
Summary: 대한민국 3대 포털뉴스(네이버, 다음, 네이트)의 기사, 반응, 댓글, 답글 수집기
Home-page: https://github.com/j1wan/portalnews
Author: Jiwan Jeong
Author-email: jiwanjeong@gmail.com
License: UNKNOWN
Platform: UNKNOWN
